odoo/addons/helpdesk_mgmt_project/README.rst
odoo/addons/helpdesk_mgmt_project/__init__.py
odoo/addons/helpdesk_mgmt_project/__manifest__.py
odoo/addons/helpdesk_mgmt_project/i18n/es.po
odoo/addons/helpdesk_mgmt_project/i18n/es_AR.po
odoo/addons/helpdesk_mgmt_project/i18n/fr.po
odoo/addons/helpdesk_mgmt_project/i18n/helpdesk_mgmt_project.pot
odoo/addons/helpdesk_mgmt_project/i18n/hu.po
odoo/addons/helpdesk_mgmt_project/i18n/it.po
odoo/addons/helpdesk_mgmt_project/i18n/pt.po
odoo/addons/helpdesk_mgmt_project/i18n/pt_BR.po
odoo/addons/helpdesk_mgmt_project/i18n/sv.po
odoo/addons/helpdesk_mgmt_project/i18n/tr.po
odoo/addons/helpdesk_mgmt_project/migrations/18.0.1.1.0/pre-migration.py
odoo/addons/helpdesk_mgmt_project/models/__init__.py
odoo/addons/helpdesk_mgmt_project/models/helpdesk_ticket.py
odoo/addons/helpdesk_mgmt_project/models/helpdesk_ticket_team.py
odoo/addons/helpdesk_mgmt_project/models/project.py
odoo/addons/helpdesk_mgmt_project/models/project_milestone.py
odoo/addons/helpdesk_mgmt_project/models/project_task.py
odoo/addons/helpdesk_mgmt_project/readme/CONTRIBUTORS.md
odoo/addons/helpdesk_mgmt_project/readme/DESCRIPTION.md
odoo/addons/helpdesk_mgmt_project/static/description/icon.png
odoo/addons/helpdesk_mgmt_project/static/description/icon.svg
odoo/addons/helpdesk_mgmt_project/static/description/index.html
odoo/addons/helpdesk_mgmt_project/tests/__init__.py
odoo/addons/helpdesk_mgmt_project/tests/test_helpdesk_ticket.py
odoo/addons/helpdesk_mgmt_project/views/helpdesk_ticket_team_view.xml
odoo/addons/helpdesk_mgmt_project/views/helpdesk_ticket_view.xml
odoo/addons/helpdesk_mgmt_project/views/project_milestone.xml
odoo/addons/helpdesk_mgmt_project/views/project_task_view.xml
odoo/addons/helpdesk_mgmt_project/views/project_view.xml
odoo_addon_helpdesk_mgmt_project-18.0.1.2.0.5.dist-info/METADATA
odoo_addon_helpdesk_mgmt_project-18.0.1.2.0.5.dist-info/WHEEL
odoo_addon_helpdesk_mgmt_project-18.0.1.2.0.5.dist-info/top_level.txt
odoo_addon_helpdesk_mgmt_project-18.0.1.2.0.5.dist-info/RECORD
